cms_forms/__init__.py
cms_forms/action_backends.py
cms_forms/action_backends_base.py
cms_forms/apps.py
cms_forms/cms_apps.py
cms_forms/cms_plugins.py
cms_forms/compat.py
cms_forms/forms.py
cms_forms/helpers.py
cms_forms/models.py
cms_forms/signals.py
cms_forms/urls.py
cms_forms/utils.py
cms_forms/validators.py
cms_forms/views.py
cms_forms/admin/__init__.py
cms_forms/admin/base.py
cms_forms/admin/exporter.py
cms_forms/admin/forms.py
cms_forms/admin/views.py
cms_forms/contrib/__init__.py
cms_forms/contrib/email_notifications/__init__.py
cms_forms/contrib/email_notifications/cms_plugins.py
cms_forms/contrib/email_notifications/helpers.py
cms_forms/contrib/email_notifications/models.py
cms_forms/contrib/email_notifications/notification.py
cms_forms/contrib/email_notifications/migrations/0001_initial.py
cms_forms/contrib/email_notifications/migrations/0002_alter_emailnotification_id.py
cms_forms/contrib/email_notifications/migrations/__init__.py
cms_forms/contrib/email_notifications/static/email_notifications/admin/email-notifications.css
cms_forms/locale/de/LC_MESSAGES/django.po
cms_forms/locale/en/LC_MESSAGES/django.po
cms_forms/locale/fa/LC_MESSAGES/django.po
cms_forms/locale/fr/LC_MESSAGES/django.po
cms_forms/locale/it/LC_MESSAGES/django.po
cms_forms/locale/lt/LC_MESSAGES/django.po
cms_forms/locale/nl/LC_MESSAGES/django.po
cms_forms/migrations/0001_initial.py
cms_forms/migrations/0002_auto_20221125_1511.py
cms_forms/migrations/0003_alter_formsubmission_language.py
cms_forms/migrations/__init__.py
cms_forms/sizefield/__init__.py
cms_forms/sizefield/models.py
cms_forms/sizefield/utils.py
cms_forms/sizefield/widgets.py
cms_forms/templates/admin/cms_forms/export.html
cms_forms/templates/admin/cms_forms/export_wizard.html
cms_forms/templates/admin/cms_forms/display/recipients.html
cms_forms/templates/admin/cms_forms/display/submission_data.html
cms_forms/templates/admin/cms_forms/formsubmission/change_list.html
cms_forms/templates/cms_forms/base.html
corebytecms_forms-1.0.1.dist-info/LICENSE
corebytecms_forms-1.0.1.dist-info/METADATA
corebytecms_forms-1.0.1.dist-info/WHEEL
corebytecms_forms-1.0.1.dist-info/top_level.txt
corebytecms_forms-1.0.1.dist-info/RECORD
