Metadata-Version: 2.1
Name: corebytecms-forms
Version: 1.0.1
Summary: Create forms and embed them on CMS pages
Home-page: https://github.com/svandeneertwegh/corebytecms-forms
Author: Corebyte
Author-email: info@corebyte.nl
License: BSD
Keywords: django django-cms form-builder form fields
Classifier: Development Status :: 5 - Production/Stable
Classifier: Environment :: Web Environment
Classifier: Intended Audience :: Developers
Classifier: License :: OSI Approved :: BSD License
Classifier: Operating System :: OS Independent
Classifier: Framework :: Django
Classifier: Framework :: Django :: 3.2
Classifier: Programming Language :: Python
Classifier: Programming Language :: Python :: 3
Classifier: Programming Language :: Python :: 3.4
Classifier: Programming Language :: Python :: 3.5
Classifier: Programming Language :: Python :: 3.6
Classifier: Programming Language :: Python :: 3.7
Classifier: Programming Language :: Python :: 3.8
Classifier: Programming Language :: Python :: 3.9
Classifier: Programming Language :: Python :: 3.10
Classifier: Topic :: Internet :: WWW/HTTP
Classifier: Topic :: Internet :: WWW/HTTP :: Dynamic Content
Classifier: Topic :: Software Development
Classifier: Topic :: Software Development :: Libraries
License-File: LICENSE
Requires-Dist: django (>=2.0<4)
Requires-Dist: django-cms (>=3.5)
Requires-Dist: djangocms-text-ckeditor
Requires-Dist: djangocms-attributes-field (>=1.0.0)
Requires-Dist: pandas
Requires-Dist: pillow
Requires-Dist: django-filer
Requires-Dist: django-sizefield
Requires-Dist: six (>=1.0)
Requires-Dist: django-simple-captcha
